oarepo_references/__init__.py
oarepo_references/api.py
oarepo_references/cli.py
oarepo_references/ext.py
oarepo_references/mixins.py
oarepo_references/models.py
oarepo_references/proxies.py
oarepo_references/signals.py
oarepo_references/utils.py
oarepo_references/version.py
oarepo_references/alembic/27aff3739ced_initialize_oarepo_references.py
oarepo_references/alembic/f2691b293c4d_create_oarepo_references_table.py
tests/__init__.py
tests/conftest.py
tests/test_api.py
tests/test_fields.py
tests/test_mixins.py
tests/test_models.py
tests/test_oarepo_references.py
tests/test_signals.py
tests/test_utils.py
oarepo_references-1.12.0.dist-info/AUTHORS.rst
oarepo_references-1.12.0.dist-info/LICENSE
oarepo_references-1.12.0.dist-info/METADATA
oarepo_references-1.12.0.dist-info/WHEEL
oarepo_references-1.12.0.dist-info/entry_points.txt
oarepo_references-1.12.0.dist-info/top_level.txt
oarepo_references-1.12.0.dist-info/RECORD
