Metadata-Version: 2.1
Name: oarepo-references
Version: 1.12.0
Summary: OArepo module for tracking and updating references in Invenio records
Home-page: https://github.com/oarepo/oarepo-references
Author: Miroslav Bauer, CESNET
Author-email: bauer@cesnet.cz
License: MIT
Platform: any
Classifier: Environment :: Web Environment
Classifier: Intended Audience :: Developers
Classifier: License :: OSI Approved :: MIT License
Classifier: Operating System :: OS Independent
Classifier: Programming Language :: Python
Classifier: Topic :: Internet :: WWW/HTTP :: Dynamic Content
Classifier: Topic :: Software Development :: Libraries :: Python Modules
Classifier: Programming Language :: Python :: 2
Classifier: Programming Language :: Python :: 2.7
Classifier: Programming Language :: Python :: 3
Classifier: Programming Language :: Python :: 3.5
Classifier: Development Status :: 4 - Beta
Provides-Extra: tests
Requires-Dist: oarepo[tests] (~=3.3.0) ; extra == 'tests'
Requires-Dist: uuid ; extra == 'tests'
Requires-Dist: oarepo-validate ; extra == 'tests'
Requires-Dist: pydocstyle ; extra == 'tests'
Requires-Dist: isort ; extra == 'tests'
Requires-Dist: check-manifest ; extra == 'tests'
Requires-Dist: pytest-cov ; extra == 'tests'
Provides-Extra: validate
Requires-Dist: oarepo-validate (>=1.1.0) ; extra == 'validate'
